<?xml version="1.0" encoding="utf-8"?>
<databaseChangeLog
    xmlns="http://www.liquibase.org/xml/ns/dbchangelog"
    xmlns:xsi="http://www.w3.org/2001/XMLSchema-instance"
    xsi:schemaLocation="http://www.liquibase.org/xml/ns/dbchangelog http://www.liquibase.org/xml/ns/dbchangelog/dbchangelog-latest.xsd">

    <changeSet id="createClasses" author="alber (generated)">
        <changeSet id="create1A" author="alber (generated)">
            <insert tableName="classe">
                <column name="indicazioneNumerica" value="1"/>
                <column name="sezione" value="A"/>
                <column name="note" value="Nessuna"/>
            </insert>
        </changeSet>

        <changeSet id="create1B" author="alber (generated)">
            <insert tableName="classe">
                <column name="indicazioneNumerica" value="1"/>
                <column name="sezione" value="B"/>
                <column name="note" value="Nessuna"/>
            </insert>
        </changeSet>

        <changeSet id="create1C" author="alber (generated)">
            <insert tableName="classe">
                <column name="indicazioneNumerica" value="1"/>
                <column name="sezione" value="C"/>
                <column name="note" value="Nessuna"/>
            </insert>
        </changeSet>

        <changeSet id="create1D" author="alber (generated)">
            <insert tableName="classe">
                <column name="indicazioneNumerica" value="1"/>
                <column name="sezione" value="D"/>
                <column name="note" value="Nessuna"/>
            </insert>
        </changeSet>

        <changeSet id="create1E" author="alber (generated)">
            <insert tableName="classe">
                <column name="indicazioneNumerica" value="1"/>
                <column name="sezione" value="E"/>
                <column name="note" value="Nessuna"/>
            </insert>
        </changeSet>

        <changeSet id="create2A" author="alber (generated)">
            <insert tableName="classe">
                <column name="indicazioneNumerica" value="2"/>
                <column name="sezione" value="A"/>
                <column name="note" value="Nessuna"/>
            </insert>
        </changeSet>

        <changeSet id="create2B" author="alber (generated)">
            <insert tableName="classe">
                <column name="indicazioneNumerica" value="2"/>
                <column name="sezione" value="B"/>
                <column name="note" value="Nessuna"/>
            </insert>
        </changeSet>

        <changeSet id="create2C" author="alber (generated)">
            <insert tableName="classe">
                <column name="indicazioneNumerica" value="2"/>
                <column name="sezione" value="C"/>
                <column name="note" value="Nessuna"/>
            </insert>
        </changeSet>

        <changeSet id="create2D" author="alber (generated)">
            <insert tableName="classe">
                <column name="indicazioneNumerica" value="2"/>
                <column name="sezione" value="D"/>
                <column name="note" value="Nessuna"/>
            </insert>
        </changeSet>

        <changeSet id="create2E" author="alber (generated)">
            <insert tableName="classe">
                <column name="indicazioneNumerica" value="2"/>
                <column name="sezione" value="E"/>
                <column name="note" value="Nessuna"/>
            </insert>
        </changeSet>

        <changeSet id="create3A" author="alber (generated)">
            <insert tableName="classe">
                <column name="indicazioneNumerica" value="2"/>
                <column name="sezione" value="A"/>
                <column name="note" value="Nessuna"/>
            </insert>
        </changeSet>

        <changeSet id="create3B" author="alber (generated)">
            <insert tableName="classe">
                <column name="indicazioneNumerica" value="3"/>
                <column name="sezione" value="B"/>
                <column name="note" value="Nessuna"/>
            </insert>
        </changeSet>

        <changeSet id="create3C" author="alber (generated)">
            <insert tableName="classe">
                <column name="indicazioneNumerica" value="3"/>
                <column name="sezione" value="C"/>
                <column name="note" value="Nessuna"/>
            </insert>
        </changeSet>

        <changeSet id="create3D" author="alber (generated)">
            <insert tableName="classe">
                <column name="indicazioneNumerica" value="3"/>
                <column name="sezione" value="D"/>
                <column name="note" value="Nessuna"/>
            </insert>
        </changeSet>

        <changeSet id="create3E" author="alber (generated)">
            <insert tableName="classe">
                <column name="indicazioneNumerica" value="3"/>
                <column name="sezione" value="E"/>
                <column name="note" value="Nessuna"/>
            </insert>
        </changeSet>

        <changeSet id="create4A" author="alber (generated)">
            <insert tableName="classe">
                <column name="indicazioneNumerica" value="4"/>
                <column name="sezione" value="A"/>
                <column name="note" value="Nessuna"/>
            </insert>
        </changeSet>

        <changeSet id="create4B" author="alber (generated)">
            <insert tableName="classe">
                <column name="indicazioneNumerica" value="4"/>
                <column name="sezione" value="B"/>
                <column name="note" value="Nessuna"/>
            </insert>
        </changeSet>

        <changeSet id="create4C" author="alber (generated)">
            <insert tableName="classe">
                <column name="indicazioneNumerica" value="4"/>
                <column name="sezione" value="C"/>
                <column name="note" value="Nessuna"/>
            </insert>
        </changeSet>

        <changeSet id="create4D" author="alber (generated)">
            <insert tableName="classe">
                <column name="indicazioneNumerica" value="4"/>
                <column name="sezione" value="D"/>
                <column name="note" value="Nessuna"/>
            </insert>
        </changeSet>

        <changeSet id="create4E" author="alber (generated)">
            <insert tableName="classe">
                <column name="indicazioneNumerica" value="4"/>
                <column name="sezione" value="E"/>
                <column name="note" value="Nessuna"/>
            </insert>
        </changeSet>

        <changeSet id="create5A" author="alber (generated)">
            <insert tableName="classe">
                <column name="indicazioneNumerica" value="5"/>
                <column name="sezione" value="A"/>
                <column name="note" value="Nessuna"/>
            </insert>
        </changeSet>

        <changeSet id="create5B" author="alber (generated)">
            <insert tableName="classe">
                <column name="indicazioneNumerica" value="5"/>
                <column name="sezione" value="B"/>
                <column name="note" value="Nessuna"/>
            </insert>
        </changeSet>

        <changeSet id="create5C" author="alber (generated)">
            <insert tableName="classe">
                <column name="indicazioneNumerica" value="5"/>
                <column name="sezione" value="C"/>
                <column name="note" value="Nessuna"/>
            </insert>
        </changeSet>

        <changeSet id="create5D" author="alber (generated)">
            <insert tableName="classe">
                <column name="indicazioneNumerica" value="5"/>
                <column name="sezione" value="D"/>
                <column name="note" value="Nessuna"/>
            </insert>
        </changeSet>

        <changeSet id="create5E" author="alber (generated)">
            <insert tableName="classe">
                <column name="indicazioneNumerica" value="5"/>
                <column name="sezione" value="E"/>
                <column name="note" value="Nessuna"/>
            </insert>
        </changeSet>


    </changeSet>

</databaseChangeLog>
